{
  "id": "249215b2-58c4-4c94-909f-31ec7f9245e6",
  "prevId": "941ad3fe-d9c2-41f4-92ec-b50cf7309638",
  "version": "7",
  "dialect": "postgresql",
  "tables": {
    "public.user_pinned_repo": {
      "name": "user_pinned_repo",
      "schema": "",
      "columns": {
        "id": {
          "name": "id",
          "type": "uuid",
          "primaryKey": true,
          "notNull": true,
          "default": "gen_random_uuid()"
        },
        "name": {
          "name": "name",
          "type": "text",
          "primaryKey": false,
          "notNull": true
        },
        "url": {
          "name": "url",
          "type": "text",
          "primaryKey": false,
          "notNull": true
        },
        "description": {
          "name": "description",
          "type": "text",
          "primaryKey": false,
          "notNull": true,
          "default": "'No description'"
        },
        "stargazer_count": {
          "name": "stargazer_count",
          "type": "integer",
          "primaryKey": false,
          "notNull": true,
          "default": 0
        },
        "fork_count": {
          "name": "fork_count",
          "type": "integer",
          "primaryKey": false,
          "notNull": true,
          "default": 0
        },
        "user_id": {
          "name": "user_id",
          "type": "uuid",
          "primaryKey": false,
          "notNull": false
        },
        "primary_language": {
          "name": "primary_language",
          "type": "text",
          "primaryKey": false,
          "notNull": true,
          "default": "'Unknown'"
        },
        "repository_topics": {
          "name": "repository_topics",
          "type": "jsonb",
          "primaryKey": false,
          "notNull": true,
          "default": "'[]'"
        },
        "languages": {
          "name": "languages",
          "type": "jsonb",
          "primaryKey": false,
          "notNull": true,
          "default": "'[]'"
        },
        "readme": {
          "name": "readme",
          "type": "text",
          "primaryKey": false,
          "notNull": true,
          "default": "'No readme.md exists'"
        },
        "created_at": {
          "name": "created_at",
          "type": "timestamp",
          "primaryKey": false,
          "notNull": true,
          "default": "now()"
        },
        "updated_at": {
          "name": "updated_at",
          "type": "timestamp",
          "primaryKey": false,
          "notNull": true,
          "default": "now()"
        }
      },
      "indexes": {},
      "foreignKeys": {
        "user_pinned_repo_user_id_users_id_fk": {
          "name": "user_pinned_repo_user_id_users_id_fk",
          "tableFrom": "user_pinned_repo",
          "tableTo": "users",
          "columnsFrom": [
            "user_id"
          ],
          "columnsTo": [
            "id"
          ],
          "onDelete": "no action",
          "onUpdate": "no action"
        }
      },
      "compositePrimaryKeys": {},
      "uniqueConstraints": {},
      "policies": {},
      "checkConstraints": {},
      "isRLSEnabled": false
    },
    "public.user_github_schema": {
      "name": "user_github_schema",
      "schema": "",
      "columns": {
        "id": {
          "name": "id",
          "type": "uuid",
          "primaryKey": true,
          "notNull": true,
          "default": "gen_random_uuid()"
        },
        "user_id": {
          "name": "user_id",
          "type": "uuid",
          "primaryKey": false,
          "notNull": true
        },
        "github_id": {
          "name": "github_id",
          "type": "text",
          "primaryKey": false,
          "notNull": true
        },
        "access_token": {
          "name": "access_token",
          "type": "text",
          "primaryKey": false,
          "notNull": true
        },
        "username": {
          "name": "username",
          "type": "text",
          "primaryKey": false,
          "notNull": true
        },
        "email": {
          "name": "email",
          "type": "text",
          "primaryKey": false,
          "notNull": true
        },
        "created_at": {
          "name": "created_at",
          "type": "timestamp",
          "primaryKey": false,
          "notNull": true,
          "default": "now()"
        },
        "updated_at": {
          "name": "updated_at",
          "type": "timestamp",
          "primaryKey": false,
          "notNull": true,
          "default": "now()"
        }
      },
      "indexes": {},
      "foreignKeys": {
        "user_github_schema_user_id_users_id_fk": {
          "name": "user_github_schema_user_id_users_id_fk",
          "tableFrom": "user_github_schema",
          "tableTo": "users",
          "columnsFrom": [
            "user_id"
          ],
          "columnsTo": [
            "id"
          ],
          "onDelete": "no action",
          "onUpdate": "no action"
        }
      },
      "compositePrimaryKeys": {},
      "uniqueConstraints": {},
      "policies": {},
      "checkConstraints": {},
      "isRLSEnabled": false
    },
    "public.linkedin_jobs": {
      "name": "linkedin_jobs",
      "schema": "",
      "columns": {
        "id": {
          "name": "id",
          "type": "uuid",
          "primaryKey": true,
          "notNull": true,
          "default": "gen_random_uuid()"
        },
        "linkedin_job_id": {
          "name": "linkedin_job_id",
          "type": "text",
          "primaryKey": false,
          "notNull": true
        },
        "job_info": {
          "name": "job_info",
          "type": "text",
          "primaryKey": false,
          "notNull": true
        },
        "created_at": {
          "name": "created_at",
          "type": "timestamp",
          "primaryKey": false,
          "notNull": true,
          "default": "now()"
        },
        "processed_skills": {
          "name": "processed_skills",
          "type": "jsonb",
          "primaryKey": false,
          "notNull": true
        },
        "updated_at": {
          "name": "updated_at",
          "type": "timestamp",
          "primaryKey": false,
          "notNull": true,
          "default": "now()"
        }
      },
      "indexes": {},
      "foreignKeys": {},
      "compositePrimaryKeys": {},
      "uniqueConstraints": {
        "linkedin_jobs_id_unique": {
          "name": "linkedin_jobs_id_unique",
          "nullsNotDistinct": false,
          "columns": [
            "id"
          ]
        },
        "linkedin_jobs_linkedin_job_id_unique": {
          "name": "linkedin_jobs_linkedin_job_id_unique",
          "nullsNotDistinct": false,
          "columns": [
            "linkedin_job_id"
          ]
        }
      },
      "policies": {},
      "checkConstraints": {},
      "isRLSEnabled": false
    },
    "public.user_saved_jobs": {
      "name": "user_saved_jobs",
      "schema": "",
      "columns": {
        "user_id": {
          "name": "user_id",
          "type": "uuid",
          "primaryKey": false,
          "notNull": true
        },
        "linkedin_job_schema_id": {
          "name": "linkedin_job_schema_id",
          "type": "uuid",
          "primaryKey": false,
          "notNull": true
        },
        "comparison": {
          "name": "comparison",
          "type": "jsonb",
          "primaryKey": false,
          "notNull": true
        },
        "saved_at": {
          "name": "saved_at",
          "type": "timestamp",
          "primaryKey": false,
          "notNull": true,
          "default": "now()"
        }
      },
      "indexes": {},
      "foreignKeys": {
        "user_saved_jobs_user_id_users_id_fk": {
          "name": "user_saved_jobs_user_id_users_id_fk",
          "tableFrom": "user_saved_jobs",
          "tableTo": "users",
          "columnsFrom": [
            "user_id"
          ],
          "columnsTo": [
            "id"
          ],
          "onDelete": "cascade",
          "onUpdate": "no action"
        },
        "user_saved_jobs_linkedin_job_schema_id_linkedin_jobs_id_fk": {
          "name": "user_saved_jobs_linkedin_job_schema_id_linkedin_jobs_id_fk",
          "tableFrom": "user_saved_jobs",
          "tableTo": "linkedin_jobs",
          "columnsFrom": [
            "linkedin_job_schema_id"
          ],
          "columnsTo": [
            "id"
          ],
          "onDelete": "cascade",
          "onUpdate": "no action"
        }
      },
      "compositePrimaryKeys": {
        "user_saved_jobs_user_id_linkedin_job_schema_id_pk": {
          "name": "user_saved_jobs_user_id_linkedin_job_schema_id_pk",
          "columns": [
            "user_id",
            "linkedin_job_schema_id"
          ]
        }
      },
      "uniqueConstraints": {},
      "policies": {},
      "checkConstraints": {},
      "isRLSEnabled": false
    },
    "public.user_leetcode_schema": {
      "name": "user_leetcode_schema",
      "schema": "",
      "columns": {
        "id": {
          "name": "id",
          "type": "uuid",
          "primaryKey": true,
          "notNull": true,
          "default": "gen_random_uuid()"
        },
        "user_id": {
          "name": "user_id",
          "type": "uuid",
          "primaryKey": false,
          "notNull": true
        },
        "leetcode_username": {
          "name": "leetcode_username",
          "type": "text",
          "primaryKey": false,
          "notNull": true
        },
        "total_solved": {
          "name": "total_solved",
          "type": "integer",
          "primaryKey": false,
          "notNull": true
        },
        "total_questions": {
          "name": "total_questions",
          "type": "integer",
          "primaryKey": false,
          "notNull": true
        },
        "easy_solved": {
          "name": "easy_solved",
          "type": "integer",
          "primaryKey": false,
          "notNull": true
        },
        "medium_solved": {
          "name": "medium_solved",
          "type": "integer",
          "primaryKey": false,
          "notNull": true
        },
        "hard_solved": {
          "name": "hard_solved",
          "type": "integer",
          "primaryKey": false,
          "notNull": true
        },
        "acceptance_rate": {
          "name": "acceptance_rate",
          "type": "integer",
          "primaryKey": false,
          "notNull": true
        },
        "ranking": {
          "name": "ranking",
          "type": "integer",
          "primaryKey": false,
          "notNull": true
        },
        "proccessed_leetcode_stat": {
          "name": "proccessed_leetcode_stat",
          "type": "jsonb",
          "primaryKey": false,
          "notNull": true
        },
        "created_at": {
          "name": "created_at",
          "type": "timestamp",
          "primaryKey": false,
          "notNull": true,
          "default": "now()"
        },
        "updated_at": {
          "name": "updated_at",
          "type": "timestamp",
          "primaryKey": false,
          "notNull": true,
          "default": "now()"
        }
      },
      "indexes": {},
      "foreignKeys": {
        "user_leetcode_schema_user_id_users_id_fk": {
          "name": "user_leetcode_schema_user_id_users_id_fk",
          "tableFrom": "user_leetcode_schema",
          "tableTo": "users",
          "columnsFrom": [
            "user_id"
          ],
          "columnsTo": [
            "id"
          ],
          "onDelete": "no action",
          "onUpdate": "no action"
        }
      },
      "compositePrimaryKeys": {},
      "uniqueConstraints": {},
      "policies": {},
      "checkConstraints": {},
      "isRLSEnabled": false
    },
    "public.users": {
      "name": "users",
      "schema": "",
      "columns": {
        "id": {
          "name": "id",
          "type": "uuid",
          "primaryKey": true,
          "notNull": true,
          "default": "gen_random_uuid()"
        },
        "avatar_url": {
          "name": "avatar_url",
          "type": "text",
          "primaryKey": false,
          "notNull": false
        },
        "resume": {
          "name": "resume",
          "type": "text",
          "primaryKey": false,
          "notNull": false
        },
        "refresh_token": {
          "name": "refresh_token",
          "type": "text",
          "primaryKey": false,
          "notNull": false
        },
        "last_login": {
          "name": "last_login",
          "type": "timestamp",
          "primaryKey": false,
          "notNull": true,
          "default": "now()"
        },
        "user_proccessed_skills": {
          "name": "user_proccessed_skills",
          "type": "jsonb",
          "primaryKey": false,
          "notNull": true,
          "default": "'[]'"
        },
        "onboarding_status": {
          "name": "onboarding_status",
          "type": "jsonb",
          "primaryKey": false,
          "notNull": true,
          "default": "'{\"github\":false,\"leetcode\":false,\"resume\":false}'::jsonb"
        },
        "created_at": {
          "name": "created_at",
          "type": "timestamp",
          "primaryKey": false,
          "notNull": true,
          "default": "now()"
        },
        "updated_at": {
          "name": "updated_at",
          "type": "timestamp",
          "primaryKey": false,
          "notNull": true,
          "default": "now()"
        }
      },
      "indexes": {},
      "foreignKeys": {},
      "compositePrimaryKeys": {},
      "uniqueConstraints": {
        "users_refresh_token_unique": {
          "name": "users_refresh_token_unique",
          "nullsNotDistinct": false,
          "columns": [
            "refresh_token"
          ]
        }
      },
      "policies": {},
      "checkConstraints": {},
      "isRLSEnabled": false
    }
  },
  "enums": {},
  "schemas": {},
  "sequences": {},
  "roles": {},
  "policies": {},
  "views": {},
  "_meta": {
    "columns": {},
    "schemas": {},
    "tables": {}
  }
}